executor/__init__.py
executor/api.py
executor/exceptions.py
executor/executors.py
executor/requests/__init__.py
executor/requests/requests.py
executor/requests/urlopen.py
executor/selenium/remote/__init__.py
executor/selenium/remote/chrome.py
executor/selenium/webdriver/__init__.py
executor/splash/__init__.py
executor/test/__init__.py
executor/utils/__init__.py
executor/utils/option.py
executor/utils/version.py
python_executor_sdk-1.0.0.dist-info/LICENSE
python_executor_sdk-1.0.0.dist-info/METADATA
python_executor_sdk-1.0.0.dist-info/WHEEL
python_executor_sdk-1.0.0.dist-info/top_level.txt
python_executor_sdk-1.0.0.dist-info/RECORD
